megha_pattern/__init__.py
megha_pattern/pattern.py
megha_pattern-1.0.0.dist-info/METADATA
megha_pattern-1.0.0.dist-info/WHEEL
megha_pattern-1.0.0.dist-info/licenses/LICENCE.txt
megha_pattern-1.0.0.dist-info/RECORD
