Metadata-Version: 2.1
Name: megha_pattern
Version: 1.0.0
Summary: This is a pattern printing program
Author-email: Megha Daw <meghadaw48954@gmail.com>
License-File: LICENCE.txt
Classifier: License :: OSI Approved :: MIT License
Classifier: Operating System :: OS Independent
Classifier: Programming Language :: Python :: 3
Requires-Python: >=3.7
